LICENSE
MANIFEST.in
README.md
pyproject.toml
setup.cfg
setup.py
django_postcodes.egg-info/PKG-INFO
django_postcodes.egg-info/SOURCES.txt
django_postcodes.egg-info/dependency_links.txt
django_postcodes.egg-info/requires.txt
django_postcodes.egg-info/top_level.txt
postcodes/__init__.py
postcodes/apps.py
postcodes/countries.py
postcodes/postcode.py
postcodes/settings.py
postcodes/urls.py
postcodes/views.py
postcodes/static/postcodes/css/postcodes.css
postcodes/static/postcodes/js/postcodes.js
postcodes/test/__init__.py
postcodes/test/manage.py
postcodes/test/testapp/__init__.py
postcodes/test/testapp/core/__init__.py
postcodes/test/testapp/core/tests.py
postcodes/test/testapp/core/migrations/__init__.py
postcodes/test/testapp/testapp/__init__.py
postcodes/test/testapp/testapp/asgi.py
postcodes/test/testapp/testapp/settings.py
postcodes/test/testapp/testapp/urls.py
postcodes/test/testapp/testapp/wsgi.py